LICENSE.txt
README.md
setup.cfg
setup.py
src/clipppy/__init__.py
src/clipppy/__init__.pyi
src/clipppy/_clipppy.py
src/clipppy/autocli.py
src/clipppy/cli.py
src/clipppy/clipppy.py
src/clipppy/helpers.py
src/clipppy.egg-info/PKG-INFO
src/clipppy.egg-info/SOURCES.txt
src/clipppy.egg-info/dependency_links.txt
src/clipppy.egg-info/requires.txt
src/clipppy.egg-info/top_level.txt
src/clipppy/commands/__init__.py
src/clipppy/commands/callbacks.py
src/clipppy/commands/command.py
src/clipppy/commands/commandable.py
src/clipppy/commands/emcee.py
src/clipppy/commands/fit.py
src/clipppy/commands/mock.py
src/clipppy/commands/optimizing_command.py
src/clipppy/commands/ppd.py
src/clipppy/commands/sampling_command.py
src/clipppy/commands/lightning/__init__.py
src/clipppy/commands/lightning/callbacks.py
src/clipppy/commands/lightning/command.py
src/clipppy/commands/lightning/hyper.py
src/clipppy/commands/lightning/loss.py
src/clipppy/commands/lightning/npe.py
src/clipppy/commands/lightning/nre.py
src/clipppy/commands/lightning/patches.py
src/clipppy/commands/lightning/config/__init__.py
src/clipppy/commands/lightning/config/schedulers.py
src/clipppy/commands/lightning/config/schedulers.pyi
src/clipppy/commands/npe/_typing.py
src/clipppy/commands/npe/nn.py
src/clipppy/commands/nre/nn.py
src/clipppy/commands/nre/validate.py
src/clipppy/distributions/__init__.py
src/clipppy/distributions/concrete.py
src/clipppy/distributions/event_masked.py
src/clipppy/distributions/igammainv.py
src/clipppy/distributions/conundis/__init__.py
src/clipppy/distributions/conundis/concrete.py
src/clipppy/distributions/conundis/constraining_messenger.py
src/clipppy/distributions/conundis/conundis_mixin.py
src/clipppy/distributions/gtflow/__init__.py
src/clipppy/distributions/gtflow/abc.py
src/clipppy/distributions/gtflow/gtflow.py
src/clipppy/distributions/gtflow/nn.py
src/clipppy/distributions/gtflow/pyro.py
src/clipppy/guide/__init__.py
src/clipppy/guide/group_spec.py
src/clipppy/guide/guide.py
src/clipppy/guide/sampling_group.py
src/clipppy/guide/sampling_groups/__init__.py
src/clipppy/guide/sampling_groups/delta.py
src/clipppy/guide/sampling_groups/diagonal_normal.py
