Metadata-Version: 2.1
Name: clipppy
Version: 0.42.0a2
Summary: Convenience Layer for Inference and Probabilistic Programming in Python
Author: Kosio Karchev
Author-email: kosioakarchev@gmail.com
License: GPLv3
Project-URL: GitHub, https://github.com/kosiokarchev/clipppy
Classifier: License :: OSI Approved :: GNU General Public License v3 (GPLv3)
Classifier: Programming Language :: Python :: 3
Classifier: Programming Language :: Python :: 3.9
Classifier: Programming Language :: Python :: 3.10
Classifier: Intended Audience :: Science/Research
Classifier: Typing :: Typed
Requires-Python: >=3.9
Provides-Extra: docs
Provides-Extra: testing
Provides-Extra: jinja
Provides-Extra: lightning
Provides-Extra: emcee
Provides-Extra: zarr
License-File: LICENSE.txt
